DEN.py
DMN.py
DSN.py
PreTrain/HpC/HBpC.py
PreTrain/HpC/HEpC.py
PreTrain/HpC/HSpC.py
PreTrain/HpC/__init__.py
PreTrain/kmeans/__init__.py
PreTrain/kmeans/bkmeans.py
PreTrain/kmeans/ekmeans.py
PreTrain/kmeans/skmeans.py
Dendrite_Neural_Network-0.0.1.dist-info/LICENSE.txt
Dendrite_Neural_Network-0.0.1.dist-info/METADATA
Dendrite_Neural_Network-0.0.1.dist-info/WHEEL
Dendrite_Neural_Network-0.0.1.dist-info/top_level.txt
Dendrite_Neural_Network-0.0.1.dist-info/RECORD
