Metadata-Version: 2.1
Name: Dendrite-Neural-Network
Version: 0.0.1
Summary: Probando...
Home-page: UNKNOWN
Author: UNKNOWN
Author-email: UNKNOWN
License: UNKNOWN
Platform: UNKNOWN
